{
  "version": 2,
  "serverId": "1518880605163618354",
  "guildId": "1518880605163618354",
  "slug": "nexus-store-618354",
  "name": "Nexus Store",
  "description": "Nexus Store uses Store Bot for digital products, orders, and verified buyer reviews.",
  "inviteCode": "zB7NgPBzBA",
  "inviteUrl": "https://discord.gg/zB7NgPBzBA",
  "verified": false,
  "stats": {
    "rating": 5,
    "reviewCount": 1,
    "completedOrders": 1,
    "positivePercent": 100,
    "activeDisputes": 0,
    "averageResponseMinutes": 0
  },
  "paymentMethods": [
    "PayPal"
  ],
  "products": [
    {
      "id": "steam",
      "name": "Steam Account",
      "price": "$10.00",
      "description": "",
      "deliveryType": "Manual delivery"
    }
  ],
  "reviews": [
    {
      "id": "aec1482a-b7e9-4208-8275-d5ab8bc4a064",
      "rating": 5,
      "text": "",
      "author": "chevette_puro",
      "createdAt": "2026-06-24T15:12:50.860Z",
      "verifiedOrder": true
    }
  ],
  "policies": {
    "refunds": "",
    "delivery": "",
    "support": ""
  },
  "tags": [
    "Reviews",
    "Products"
  ],
  "lastUpdated": "2026-06-24T15:30:01.607Z"
}
